Workbook

Sheet Supuestos
A1: FoodSense · Supuestos editables
A3: Variable | B3: Valor | C3: Unidad / nota
A4: Precio mensual Plus | B4: 2.99 | C4: USD/mes
A5: Precio anual Plus | B5: 24.99 | C5: USD/año
A6: Mezcla anual | B6: 0.7 | C6: % de suscriptores
A7: Mezcla mensual | B7: =1-B6 -> 0.3 | C7: % de suscriptores
A8: ARPPU anual combinado | B8: =B5*B6+B4*12*B7 -> 28.257 | C8: USD/año
A9: TAM | B9: 15699016 | C9: viviendas particulares ocupadas
A10: Acceso internet urbano | B10: 0.937 | C10: proxy INDEC
A11: SAM | B11: =B9*B10 -> 14709978 | C11: hogares conectados aproximados
A12: SOM base año 1 | B12: 12000 | C12: hogares activos promedio
A14: Celdas verdes: supuestos que pueden editarse. Las fórmulas se recalculan automáticamente.

Sheet Escenarios
A1: Escenarios de facturación anual bruta
A3: Escenario | B3: Hogares activos | C3: Conversión | D3: Hogares pagos | E3: ARPPU | F3: B2C | G3: Contratos B2B | H3: Ticket B2B | I3: B2B | J3: Total
A4: Conservador | B4: 5000 | C4: 0.03 | D4: =B4*C4 -> 150 | E4: =Supuestos!B8 -> 28.257 | F4: =D4*E4 -> 4238.55 | G4: 1 | H4: 10000 | I4: =G4*H4 -> 10000 | J4: =F4+I4 -> 14238.55
A5: Base | B5: 12000 | C5: 0.04 | D5: =B5*C5 -> 480 | E5: =Supuestos!B8 -> 28.257 | F5: =D5*E5 -> 13563.36 | G5: 2 | H5: 15000 | I5: =G5*H5 -> 30000 | J5: =F5+I5 -> 43563.36
A6: Optimista | B6: 30000 | C6: 0.06 | D6: =B6*C6 -> 1800 | E6: =Supuestos!B8 -> 28.257 | F6: =D6*E6 -> 50862.6 | G6: 4 | H6: 20000 | I6: =G6*H6 -> 80000 | J6: =F6+I6 -> 130862.6
A8: Nota | B8: Facturación bruta: no descuenta impuestos, costos de pago, infraestructura, IA, soporte ni ventas.

Sheet Mercado
A1: TAM · SAM · SOM
A3: Nivel | B3: Valor | C3: Cálculo | D3: Fuente / limitación
A4: TAM | B4: =Supuestos!B9 -> 15699016 | C4: Viviendas particulares ocupadas | D4: INDEC, Censo 2022
A5: SAM | B5: =Supuestos!B11 -> 14709978 | C5: TAM × 93,7% | D5: Proxy: conectividad urbana aplicada al TAM
A6: SOM | B6: =Supuestos!B12 -> 12000 | C6: Meta año 1 | D6: Hipótesis de hogares activos promedio
A7: SOM / SAM | B7: =B6/B5 -> 0.0008157728 | C7: Penetración requerida | D7: Debe revisarse con datos de adquisición

Sheet Sensibilidad
A1: Sensibilidad B2C: facturación anual según adopción
A3: Hogares activos | B3: 0.02 | C3: 0.03 | D3: 0.04 | E3: 0.05 | F3: 0.06 | G3: 0.07 | H3: 0.08
A4: 5000 | B4: =$A4*B$3*Supuestos!$B$8 -> 2825.7 | C4: =$A4*C$3*Supuestos!$B$8 -> 4238.55 | D4: =$A4*D$3*Supuestos!$B$8 -> 5651.4 | E4: =$A4*E$3*Supuestos!$B$8 -> 7064.25 | F4: =$A4*F$3*Supuestos!$B$8 -> 8477.1 | G4: =$A4*G$3*Supuestos!$B$8 -> 9889.95 | H4: =$A4*H$3*Supuestos!$B$8 -> 11302.8
A5: 12000 | B5: =$A5*B$3*Supuestos!$B$8 -> 6781.68 | C5: =$A5*C$3*Supuestos!$B$8 -> 10172.52 | D5: =$A5*D$3*Supuestos!$B$8 -> 13563.36 | E5: =$A5*E$3*Supuestos!$B$8 -> 16954.2 | F5: =$A5*F$3*Supuestos!$B$8 -> 20345.04 | G5: =$A5*G$3*Supuestos!$B$8 -> 23735.88 | H5: =$A5*H$3*Supuestos!$B$8 -> 27126.72
A6: 30000 | B6: =$A6*B$3*Supuestos!$B$8 -> 16954.2 | C6: =$A6*C$3*Supuestos!$B$8 -> 25431.3 | D6: =$A6*D$3*Supuestos!$B$8 -> 33908.4 | E6: =$A6*E$3*Supuestos!$B$8 -> 42385.5 | F6: =$A6*F$3*Supuestos!$B$8 -> 50862.6 | G6: =$A6*G$3*Supuestos!$B$8 -> 59339.7 | H6: =$A6*H$3*Supuestos!$B$8 -> 67816.8
A7: 50000 | B7: =$A7*B$3*Supuestos!$B$8 -> 28257 | C7: =$A7*C$3*Supuestos!$B$8 -> 42385.5 | D7: =$A7*D$3*Supuestos!$B$8 -> 56514 | E7: =$A7*E$3*Supuestos!$B$8 -> 70642.5 | F7: =$A7*F$3*Supuestos!$B$8 -> 84771 | G7: =$A7*G$3*Supuestos!$B$8 -> 98899.5 | H7: =$A7*H$3*Supuestos!$B$8 -> 113028
A10: La sensibilidad muestra sólo B2C; los contratos B2B se modelan por separado.

Sheet Gráficos
A1: Gráficos vinculados a los escenarios
A3: Escenario | B3: B2C | C3: B2B | D3: Total
A4: =Escenarios!A4 -> Conservador | B4: =Escenarios!F4 -> 4238.55 | C4: =Escenarios!I4 -> 10000 | D4: =Escenarios!J4 -> 14238.55
A5: =Escenarios!A5 -> Base | B5: =Escenarios!F5 -> 13563.36 | C5: =Escenarios!I5 -> 30000 | D5: =Escenarios!J5 -> 43563.36
A6: =Escenarios!A6 -> Optimista | B6: =Escenarios!F6 -> 50862.6 | C6: =Escenarios!I6 -> 80000 | D6: =Escenarios!J6 -> 130862.6
